dewan_h5/DewanH5.py
dewan_h5/__init__.py
dewan_h5/__main__.py
dewan_h5/test.py
dewan_h5-1.2.5.dist-info/METADATA
dewan_h5-1.2.5.dist-info/WHEEL
dewan_h5-1.2.5.dist-info/top_level.txt
dewan_h5-1.2.5.dist-info/RECORD
