Metadata-Version: 2.4
Name: dewan_h5
Version: 1.2.5
Summary: Python package to load and parse H5 files in the Dewan Lab.
Author-email: Austin Pauley <pauley@psy.fsu.edu>
License-Expression: MIT
Project-URL: Homepage, https://github.com/olfactorybehaviorlab/dewan_h5
Requires-Python: >=3.12
Requires-Dist: h5py
Requires-Dist: openpyxl>=3.1.5
Requires-Dist: pandas
Requires-Dist: numpy
